erlab/__init__.py
erlab/accessors/__init__.py
erlab/accessors/fit.py
erlab/accessors/general.py
erlab/accessors/kspace.py
erlab/accessors/utils.py
erlab/analysis/__init__.py
erlab/analysis/__init__.pyi
erlab/analysis/correlation.py
erlab/analysis/fit/__init__.py
erlab/analysis/fit/__init__.pyi
erlab/analysis/fit/functions/__init__.py
erlab/analysis/fit/functions/__init__.pyi
erlab/analysis/fit/functions/dynamic.py
erlab/analysis/fit/functions/general.py
erlab/analysis/fit/minuit.py
erlab/analysis/fit/models.py
erlab/analysis/fit/spline.py
erlab/analysis/gold.py
erlab/analysis/image.py
erlab/analysis/interpolate.py
erlab/analysis/kspace.py
erlab/analysis/mask/__init__.py
erlab/analysis/mask/polygon.py
erlab/analysis/mesh.py
erlab/analysis/transform.py
erlab/constants.py
erlab/interactive/__init__.py
erlab/interactive/__init__.pyi
erlab/interactive/_dask.py
erlab/interactive/_fit1d.py
erlab/interactive/_fit2d.py
erlab/interactive/_magic.py
erlab/interactive/_mesh.py
erlab/interactive/_options/__init__.py
erlab/interactive/_options/__init__.pyi
erlab/interactive/_options/core.py
erlab/interactive/_options/parameters.py
erlab/interactive/_options/schema.py
erlab/interactive/_options/tree.py
erlab/interactive/_options/ui.py
erlab/interactive/bzplot.py
erlab/interactive/colors.py
erlab/interactive/curvefittingtool.py
erlab/interactive/derivative.py
erlab/interactive/dtool.ui
erlab/interactive/explorer/__init__.py
erlab/interactive/explorer/__main__.py
erlab/interactive/explorer/_base_explorer.py
erlab/interactive/explorer/_tabbed_explorer.py
erlab/interactive/fermiedge.py
erlab/interactive/imagetool/__init__.py
erlab/interactive/imagetool/__init__.pyi
erlab/interactive/imagetool/_deprecated/__init__.py
erlab/interactive/imagetool/_deprecated/imagetool_mpl.py
erlab/interactive/imagetool/_deprecated/imagetool_old.py
erlab/interactive/imagetool/_history.py
erlab/interactive/imagetool/_itool.py
erlab/interactive/imagetool/_magic.py
erlab/interactive/imagetool/_mainwindow.py
erlab-3.19.0.dist-info/WHEEL
erlab-3.19.0.dist-info/entry_points.txt
erlab-3.19.0.dist-info/METADATA
erlab-3.19.0.dist-info/RECORD
