Metadata-Version: 2.3
Name: erlab
Version: 3.19.0
Summary: Python package for ARPES data analysis and visualization.
Keywords: Condensed Matter Physics,ARPES
Author: Kimoon Higashihira Han
Author-email: Kimoon Higashihira Han <khan@kaist.ac.kr>
License:                     GNU GENERAL PUBLIC LICENSE
Classifier: Development Status :: 4 - Beta
Classifier: Intended Audience :: Science/Research
Classifier: Topic :: Scientific/Engineering :: Physics
Classifier: Topic :: Scientific/Engineering :: Visualization
Classifier: License :: OSI Approved :: GNU General Public License v3 or later (GPLv3+)
Classifier: Programming Language :: Python :: 3.11
Classifier: Programming Language :: Python :: 3.12
Classifier: Programming Language :: Python :: 3.13
Classifier: Programming Language :: Python :: 3.14
Classifier: Operating System :: OS Independent
Requires-Dist: dask[distributed]>=2024.4.1
Requires-Dist: findiff>=0.12.0
Requires-Dist: h5netcdf>=1.7.1
Requires-Dist: igor2>=0.5.12
Requires-Dist: igorwriter>=0.6.1
Requires-Dist: joblib>=1.3.2
Requires-Dist: lazy-loader>=0.4
Requires-Dist: lmfit>=1.3.2
Requires-Dist: matplotlib>=3.8.0
Requires-Dist: numba>=0.63.0 ; platform_machine != 'x86_64' or sys_platform != 'darwin'
Requires-Dist: numba>=0.61.0,<0.63.0 ; platform_machine == 'x86_64' and sys_platform == 'darwin'
Requires-Dist: numexpr>=2.11.0
Requires-Dist: numpy>=1.26.0
Requires-Dist: packaging>=24.0
Requires-Dist: pickleshare>=0.7.5
Requires-Dist: pydantic>=2.11.7
Requires-Dist: pyperclip>=1.8.2
Requires-Dist: pyqtgraph>=0.13.1
Requires-Dist: pyzmq>=27.0.2
Requires-Dist: qtawesome>=1.3.1
Requires-Dist: qtconsole>=5.6.0
Requires-Dist: qtpy>=2.4.1
Requires-Dist: scipy>=1.15.0
Requires-Dist: tqdm>=4.66.2
Requires-Dist: varname>=0.13.0
Requires-Dist: xarray>=2024.10.0
Requires-Dist: xarray-lmfit>=0.5.4
Requires-Dist: pygments>=2.11.0
Requires-Dist: erlab[viz,io,perf,misc] ; extra == 'complete'
Requires-Dist: astropy>=5.1.1 ; extra == 'io'
Requires-Dist: libarchive-c>=5.2 ; extra == 'io'
Requires-Dist: nexusformat>=1.0.6 ; extra == 'io'
Requires-Dist: zarr>=3.1.2 ; extra == 'io'
Requires-Dist: iminuit>=2.25.2,!=2.31.2 ; extra == 'misc'
Requires-Dist: csaps>=1.1.0 ; extra == 'misc'
Requires-Dist: numdifftools>=0.9.42 ; extra == 'misc'
Requires-Dist: numbagg>=0.8.1 ; extra == 'perf'
Requires-Dist: xxhash>=3.5.0 ; extra == 'perf'
Requires-Dist: hvplot>=0.11.0,!=0.12.0 ; extra == 'viz'
Requires-Dist: ipywidgets ; extra == 'viz'
Requires-Python: >=3.11
Project-URL: Changelog, https://github.com/kmnhan/erlabpy/blob/main/CHANGELOG.md
Project-URL: Documentation, https://erlabpy.readthedocs.io
Project-URL: Issues, https://github.com/kmnhan/erlabpy/issues
Project-URL: Repository, https://github.com/kmnhan/erlabpy.git
Provides-Extra: complete
Provides-Extra: io
Provides-Extra: misc
Provides-Extra: perf
Provides-Extra: viz
